Workbook
Name Slicer_City: #N/A
Name Slicer_Payment: #N/A
Name Slicer_Product: #N/A

Sheet pivot1
A3: City | B3: Sum of Sales
A4: Bangalore | B4: 173900
A5: Delhi | B5: 306600
A6: Mumbai | B6: 243200
A7: Pune | B7: 169200
A8: Grand Total | B8: 892900

Sheet Dashboard Sheet
A3: Total Revenue | B3: Total Orders | C3: Average Sales | D3: High Sales Orders
A4: =SUM(Dataset!H2:H42) -> 892900 | B4: 40 | C4: =AVERAGE(Dataset!H2:H43) -> 22322.5 | D4: 15

Sheet pivot2
A3: Product | B3: Sum of Sales
A4: Chair | B4: 52700
A5: Headphones | B5: 61900
A6: Laptop | B6: 446000
A7: Mobile | B7: 259000
A8: Table | B8: 73300
A9: Grand Total | B9: 892900

Sheet pivot3
A3: Payment | B3: Sum of Sales
A4: Card | B4: 250000
A5: Cash | B5: 208400
A6: UPI | B6: 434500
A7: Grand Total | B7: 892900

Sheet Dataset
A1: Order_ID | B1: Customer | C1: City | D1: Product | E1: Category | F1: Price | G1: Quantity | H1: Sales | I1: Payment | J1: Standard Price | K1: Sales Type | M1: City | N1: Order | O1: Revenue
A2: 1001 | B2: Amit | C2: Delhi | D2: Laptop | E2: Electronics | F2: 55000 | G2: 1 | H2: 55000 | I2: UPI | J2: =VLOOKUP(D2,Product_Master!A:B,2,FALSE) -> 55000 | K2: =IF(H2>20000,"High","Low") -> High | M2: Delhi | N2: =COUNTIF(C2:C41,"Delhi") -> 14 | O2: =SUMIF(Table1[[#This Row],[City]],"Delhi",Table1[[#This Row],[Sales]]) -> 55000
A3: 1002 | B3: Riya | C3: Mumbai | D3: Mobile | E3: Electronics | F3: 20000 | G3: 2 | H3: 40000 | I3: Card | J3: =VLOOKUP(D3,Product_Master!A:B,2,FALSE) -> 22000 | K3: =IF(H3>20000,"High","Low") -> High | M3: Mumbai | N3: =COUNTIF(C2:C41,"Mumbai") -> 9 | O3: =SUMIF(Table1[[#This Row],[City]],"Mumbai",Table1[[#This Row],[Sales]]) -> 40000
A4: 1003 | B4: Karan | C4: Delhi | D4: Headphones | E4: Electronics | F4: 3000 | G4: 3 | H4: 9000 | I4: Cash | J4: =VLOOKUP(D4,Product_Master!A:B,2,FALSE) -> 3200 | K4: =IF(H4>20000,"High","Low") -> Low | M4: Pune | N4: =COUNTIF(C2:C41,"Pune") -> 8 | O4: =SUMIF(C2:C41,"Pune",H2:H41) -> 169200
A5: 1004 | B5: Neha | C5: Pune | D5: Chair | E5: Furniture | F5: 4500 | G5: 2 | H5: 9000 | I5: UPI | J5: =VLOOKUP(D5,Product_Master!A:B,2,FALSE) -> 4800 | K5: =IF(H5>20000,"High","Low") -> Low | M5: Bangalore | N5: =COUNTIF(C2:C41,"Bangalore") -> 9 | O5: =SUMIF(C2:C41,"Bangalore",H2:H41) -> 173900
A6: 1005 | B6: Rahul | C6: Delhi | D6: Table | E6: Furniture | F6: 7000 | G6: 1 | H6: 7000 | I6: Card | J6: =VLOOKUP(D6,Product_Master!A:B,2,FALSE) -> 7500 | K6: =IF(H6>20000,"High","Low") -> Low
A7: 1006 | B7: Sneha | C7: Bangalore | D7: Laptop | E7: Electronics | F7: 56000 | G7: 1 | H7: 56000 | I7: UPI | J7: =VLOOKUP(D7,Product_Master!A:B,2,FALSE) -> 55000 | K7: =IF(H7>20000,"High","Low") -> High
A8: 1007 | B8: Vikas | C8: Mumbai | D8: Mobile | E8: Electronics | F8: 22000 | G8: 2 | H8: 44000 | I8: Cash | J8: =VLOOKUP(D8,Product_Master!A:B,2,FALSE) -> 22000 | K8: =IF(H8>20000,"High","Low") -> High
A9: 1008 | B9: Pooja | C9: Pune | D9: Chair | E9: Furniture | F9: 4800 | G9: 1 | H9: 4800 | I9: UPI | J9: =VLOOKUP(D9,Product_Master!A:B,2,FALSE) -> 4800 | K9: =IF(H9>20000,"High","Low") -> Low
A10: 1009 | B10: Arjun | C10: Delhi | D10: Table | E10: Furniture | F10: 7500 | G10: 1 | H10: 7500 | I10: Card | J10: =VLOOKUP(D10,Product_Master!A:B,2,FALSE) -> 7500 | K10: =IF(H10>20000,"High","Low") -> Low
A11: 1010 | B11: Meera | C11: Bangalore | D11: Headphones | E11: Electronics | F11: 3200 | G11: 2 | H11: 6400 | I11: UPI | J11: =VLOOKUP(D11,Product_Master!A:B,2,FALSE) -> 3200 | K11: =IF(H11>20000,"High","Low") -> Low
A12: 1011 | B12: Rohit | C12: Delhi | D12: Laptop | E12: Electronics | F12: 54000 | G12: 1 | H12: 54000 | I12: Card | J12: =VLOOKUP(D12,Product_Master!A:B,2,FALSE) -> 55000 | K12: =IF(H12>20000,"High","Low") -> High
A13: 1012 | B13: Anjali | C13: Mumbai | D13: Mobile | E13: Electronics | F13: 21000 | G13: 1 | H13: 21000 | I13: UPI | J13: =VLOOKUP(D13,Product_Master!A:B,2,FALSE) -> 22000 | K13: =IF(H13>20000,"High","Low") -> High
A14: 1013 | B14: Sumit | C14: Pune | D14: Table | E14: Furniture | F14: 7200 | G14: 2 | H14: 14400 | I14: Cash | J14: =VLOOKUP(D14,Product_Master!A:B,2,FALSE) -> 7500 | K14: =IF(H14>20000,"High","Low") -> Low
A15: 1014 | B15: Priya | C15: Delhi | D15: Chair | E15: Furniture | F15: 4600 | G15: 1 | H15: 4600 | I15: UPI | J15: =VLOOKUP(D15,Product_Master!A:B,2,FALSE) -> 4800 | K15: =IF(H15>20000,"High","Low") -> Low
A16: 1015 | B16: Kunal | C16: Bangalore | D16: Headphones | E16: Electronics | F16: 3500 | G16: 2 | H16: 7000 | I16: Card | J16: =VLOOKUP(D16,Product_Master!A:B,2,FALSE) -> 3200 | K16: =IF(H16>20000,"High","Low") -> Low
A17: 1016 | B17: Simran | C17: Mumbai | D17: Laptop | E17: Electronics | F17: 57000 | G17: 1 | H17: 57000 | I17: UPI | J17: =VLOOKUP(D17,Product_Master!A:B,2,FALSE) -> 55000 | K17: =IF(H17>20000,"High","Low") -> High
... A41: 1040 | B41: Ankit | C41: Bangalore | D41: Headphones | E41: Electronics | F41: 3600 | G41: 2 | H41: 7200 | I41: UPI | J41: =VLOOKUP(D41,Product_Master!A:B,2,FALSE) -> 3200 | K41: =IF(H41>20000,"High","Low") -> Low

Sheet Product_Master
A1: Product | B1: Standard Price
A2: Laptop | B2: 55000
A3: Mobile | B3: 22000
A4: Headphones | B4: 3200
A5: Chair | B5: 4800
A6: Table | B6: 7500
